cache
dist
docs
notebooks
scripts
waste_flow
