Metadata-Version: 2.1
Name: waste-flow
Version: 1.3.2
Summary: A package for retrieving data concerning waste management on the European continent.
Home-page: http://github.com/xapple/waste_flow/
Author: Lucas Sinclair
Author-email: lucas.sinclair@me.com
License: MIT
Platform: UNKNOWN
Requires-Python: >=3.6
License-File: LICENSE.txt
